{"stats":{"minecraft:used":{"minecraft:diamond_boots":1,"minecraft:baked_potato":11,"minecraft:ender_pearl":8,"minecraft:diamond_chestplate":1,"minecraft:diamond_sword":212,"minecraft:cobblestone":14,"minecraft:diamond_helmet":1,"minecraft:diamond_leggings":1,"minecraft:splash_potion":54},"minecraft:dropped":{"minecraft:diamond_sword":2,"minecraft:diamond_chestplate":2,"minecraft:baked_potato":60,"minecraft:diamond_leggings":2,"minecraft:diamond_helmet":2,"minecraft:cobblestone":1,"minecraft:diamond_boots":3,"minecraft:splash_potion":9},"minecraft:custom":{"minecraft:time_since_rest":1118,"minecraft:sprint_one_cm":103633,"minecraft:damage_taken":4143,"minecraft:walk_one_cm":45305,"minecraft:drop":22,"minecraft:damage_dealt":4714,"minecraft:swim_one_cm":506,"minecraft:player_kills":1,"minecraft:fly_one_cm":105291,"minecraft:crouch_one_cm":1314,"minecraft:play_time":23121,"minecraft:deaths":3,"minecraft:sneak_time":553,"minecraft:walk_under_water_one_cm":356,"minecraft:jump":653,"minecraft:leave_game":9,"minecraft:time_since_death":1098,"minecraft:walk_on_water_one_cm":1145,"minecraft:climb_one_cm":5398,"minecraft:total_world_time":23121,"minecraft:fall_one_cm":13731},"minecraft:killed_by":{"minecraft:player":3},"minecraft:picked_up":{"minecraft:splash_potion":10,"minecraft:diamond_sword":2,"minecraft:ink_sac":1,"minecraft:diamond_chestplate":2,"minecraft:diamond_leggings":2,"minecraft:diamond_boots":2,"minecraft:diamond_helmet":2,"minecraft:baked_potato":123,"minecraft:cobblestone":1,"minecraft:ender_pearl":13}},"DataVersion":3120}