{"stats":{"minecraft:used":{"minecraft:diamond_sword":131,"minecraft:diamond_pickaxe":9,"minecraft:cobblestone":20,"minecraft:golden_carrot":8,"minecraft:ender_pearl":8,"minecraft:splash_potion":56,"minecraft:cobweb":13},"minecraft:killed_by":{"minecraft:player":1},"minecraft:custom":{"minecraft:time_since_rest":592,"minecraft:deaths":1,"minecraft:crouch_one_cm":1397,"minecraft:play_time":29151,"minecraft:sprint_one_cm":130638,"minecraft:open_shulker_box":1,"minecraft:damage_taken":3716,"minecraft:walk_one_cm":106211,"minecraft:sneak_time":491,"minecraft:walk_under_water_one_cm":170,"minecraft:drop":3,"minecraft:jump":406,"minecraft:damage_dealt":3059,"minecraft:leave_game":1,"minecraft:walk_on_water_one_cm":5273,"minecraft:time_since_death":589,"minecraft:total_world_time":29151,"minecraft:interact_with_crafting_table":3,"minecraft:fall_one_cm":14530,"minecraft:player_kills":1,"minecraft:fly_one_cm":53621},"minecraft:mined":{"minecraft:stone_slab":1,"minecraft:cobblestone":7,"minecraft:shulker_box":1,"minecraft:wall_torch":2},"minecraft:dropped":{"minecraft:oak_planks":64,"minecraft:stick":6},"minecraft:picked_up":{"minecraft:splash_potion":1,"minecraft:stick":6,"minecraft:torch":1,"minecraft:cobblestone":40,"minecraft:ender_pearl":2}},"DataVersion":3218}