{"stats":{"minecraft:used":{"minecraft:diamond_sword":560,"minecraft:cobblestone":41,"minecraft:golden_carrot":19,"minecraft:ender_pearl":21,"minecraft:splash_potion":68},"minecraft:dropped":{"minecraft:cobblestone":64,"minecraft:diamond_sword":2,"minecraft:diamond_boots":1,"minecraft:diamond_chestplate":2,"minecraft:ender_pearl":16,"minecraft:splash_potion":1,"minecraft:diamond_helmet":1,"minecraft:diamond_leggings":1},"minecraft:custom":{"minecraft:time_since_rest":19638,"minecraft:crouch_one_cm":7117,"minecraft:damage_taken":5273,"minecraft:play_time":27024,"minecraft:sprint_one_cm":164766,"minecraft:walk_one_cm":55025,"minecraft:deaths":1,"minecraft:sneak_time":1986,"minecraft:walk_under_water_one_cm":2108,"minecraft:drop":10,"minecraft:jump":1104,"minecraft:damage_dealt":11758,"minecraft:leave_game":3,"minecraft:walk_on_water_one_cm":26572,"minecraft:time_since_death":19635,"minecraft:total_world_time":27024,"minecraft:swim_one_cm":5837,"minecraft:interact_with_crafting_table":1,"minecraft:fall_one_cm":49736,"minecraft:fly_one_cm":215331,"minecraft:player_kills":11},"minecraft:killed_by":{"minecraft:player":1},"minecraft:picked_up":{"minecraft:splash_potion":40,"minecraft:golden_carrot":62,"minecraft:diamond_chestplate":2,"minecraft:diamond_leggings":2,"minecraft:diamond_sword":5,"minecraft:diamond_boots":1,"minecraft:diamond_helmet":3,"minecraft:cobblestone":62,"minecraft:ender_pearl":55}},"DataVersion":3120}