{"stats":{"minecraft:used":{"minecraft:diamond_pickaxe":37,"minecraft:ender_pearl":19,"minecraft:torch":1,"minecraft:diamond_sword":703,"minecraft:cobblestone":214,"minecraft:golden_carrot":29,"minecraft:splash_potion":314},"minecraft:dropped":{"minecraft:diamond_sword":6,"minecraft:diamond_chestplate":8,"minecraft:diamond_pickaxe":5,"minecraft:ender_pearl":62,"minecraft:diamond_leggings":3,"minecraft:diamond_helmet":6,"minecraft:cobblestone":147,"minecraft:diamond_shovel":1,"minecraft:oak_planks":64,"minecraft:diamond_boots":7,"minecraft:string":1,"minecraft:splash_potion":1},"minecraft:mined":{"minecraft:soul_sand":1,"minecraft:cobblestone_stairs":1,"minecraft:torch":1,"minecraft:cobblestone":34,"minecraft:oak_planks":1,"minecraft:diorite":1,"minecraft:tripwire":1,"minecraft:wall_torch":1},"minecraft:custom":{"minecraft:time_since_rest":1,"minecraft:sprint_one_cm":412060,"minecraft:damage_taken":22921,"minecraft:walk_one_cm":264283,"minecraft:drop":49,"minecraft:damage_dealt":14990,"minecraft:swim_one_cm":1701,"minecraft:interact_with_crafting_table":3,"minecraft:fly_one_cm":161008,"minecraft:player_kills":5,"minecraft:open_chest":1,"minecraft:crouch_one_cm":2018,"minecraft:play_time":86559,"minecraft:deaths":11,"minecraft:sneak_time":1698,"minecraft:walk_under_water_one_cm":18855,"minecraft:jump":1781,"minecraft:leave_game":6,"minecraft:walk_on_water_one_cm":7956,"minecraft:time_since_death":0,"minecraft:total_world_time":86559,"minecraft:fall_one_cm":59204},"minecraft:killed_by":{"minecraft:player":11},"minecraft:broken":{"minecraft:diamond_helmet":2},"minecraft:picked_up":{"minecraft:coarse_dirt":1,"minecraft:splash_potion":85,"minecraft:golden_carrot":295,"minecraft:torch":1,"minecraft:diamond_sword":8,"minecraft:diorite":1,"minecraft:string":1,"minecraft:diamond_shovel":1,"minecraft:diamond_chestplate":4,"minecraft:diamond_leggings":3,"minecraft:diamond_boots":1,"minecraft:diamond_helmet":2,"minecraft:oak_planks":128,"minecraft:soul_sand":1,"minecraft:diamond_pickaxe":4,"minecraft:cobblestone":118,"minecraft:ender_pearl":110}},"DataVersion":3120}